pyfltr/__init__.py
pyfltr/__main__.py
pyfltr/cli.py
pyfltr/command.py
pyfltr/config.py
pyfltr/main.py
pyfltr/ui.py
pyfltr-1.13.0.dist-info/METADATA
pyfltr-1.13.0.dist-info/WHEEL
pyfltr-1.13.0.dist-info/entry_points.txt
pyfltr-1.13.0.dist-info/licenses/LICENSE
pyfltr-1.13.0.dist-info/RECORD
