Metadata-Version: 2.4
Name: pyfltr
Version: 1.13.0
Summary: Python Formatters, Linters, and Testers Runner.
Project-URL: Homepage, https://github.com/ak110/pyfltr
Author-email: "aki." <mark@aur.ll.to>
License: MIT
License-File: LICENSE
Classifier: Environment :: Console
Classifier: Intended Audience :: Developers
Classifier: Operating System :: OS Independent
Classifier: Programming Language :: Python :: 3 :: Only
Classifier: Topic :: Software Development :: Quality Assurance
Requires-Python: <4.0,>=3.11
Requires-Dist: autoflake>=2.0
Requires-Dist: black>=22.0
Requires-Dist: dill>=0.3
Requires-Dist: flake8-bugbear>=23.0
Requires-Dist: flake8-tidy-imports>=4.11.0
Requires-Dist: isort>=5.0
Requires-Dist: mypy>=1.0
Requires-Dist: natsort>=8.4.0
Requires-Dist: pylint>=3.0
Requires-Dist: pyproject-flake8>=7.0
Requires-Dist: pytest-asyncio>=1.0.0
Requires-Dist: pytest>=7.0
Requires-Dist: pyupgrade>=3.0
Requires-Dist: ruff>=0.12.1
Requires-Dist: textual>=0.80.0
Provides-Extra: pyright
Requires-Dist: pyright[nodejs]>=1.1.403; extra == 'pyright'
